{
    "id": 8840,
    "title": "Input Validation and Conversion",
    "description": "Write a program that takes a string input from the user, checks if it can be converted to an integer, and then prints out the integer value if successful. If the input cannot be converted, print an error message. Additionally, the program should also handle cases where the input is empty.",
    "difficulty": "hard",
    "topics": [
        "input/output",
        "error handling",
        "type conversion"
    ],
    "sample_input": "123",
    "sample_output": "Integer value: 123"
}