{
    "id": 7377,
    "title": "Calculating Area and Perimeter using Functions",
    "description": "Create a program that calculates the area and perimeter of a rectangle using functions. The program should have two functions: one for calculating the area and one for calculating the perimeter. The rectangle's length and width should be provided as input to the program.",
    "difficulty": "god",
    "topics": [
        "functions"
    ],
    "sample_input": "10 5",
    "sample_output": "Area: 50, Perimeter: 30"
}