{
    "id": 7882,
    "title": "String Reversal and Palindrome Check",
    "description": "Write a program that takes a string input from the user, reverses the string, and checks if the reversed string is a palindrome. A palindrome is a word, phrase, number, or other sequence of characters that reads the same forward and backward (ignoring spaces, punctuation, and capitalization).",
    "difficulty": "superhard",
    "topics": [
        "string manipulation",
        "looping",
        "conditional statements"
    ],
    "sample_input": "Madam",
    "sample_output": "The reversed string is: madam. The string is a palindrome."
}