{
    "id": 375,
    "title": "GradeCalculator",
    "description": "Create a program that calculates the grade of a student based on their score. The program should take the score as input and output the corresponding grade. The grades are as follows: A (90-100), B (80-89), C (70-79), D (60-69), F (below 60). Use conditional statements to determine the grade.",
    "difficulty": "hard",
    "topics": [
        "conditional statements",
        "if/else"
    ],
    "sample_input": "85",
    "sample_output": "B"
}