{
    "id": 7273,
    "title": "Calculator Program",
    "description": "Create a program that performs arithmetic operations based on user input. The program should take two numbers and an operator as input and print the result. The operators to support are +, -, *, /, and %. The program should handle invalid inputs and division by zero errors.",
    "difficulty": "superhard",
    "topics": [
        "arithmetic operations",
        "error handling",
        "user input"
    ],
    "sample_input": "10 + 5",
    "sample_output": "15"
}