{
    "id": 7027,
    "title": "Student Grades Dictionary",
    "description": "Create a function that takes a dictionary where the keys are student names and the values are lists of their grades. The function should return a new dictionary where the keys are the student names and the values are their average grades. Round the average grades to two decimal places.",
    "difficulty": "easy",
    "topics": [
        "dictionaries"
    ],
    "sample_input": "{\"John\": [90, 80, 70], \"Alice\": [95, 85, 75]}",
    "sample_output": "{\"John\": 80.0, \"Alice\": 85.0}"
}