{
    "id": 7758,
    "title": "Input/Output Master",
    "description": "Create a program that reads a user's name, age, and favorite color from the input, then prints out a personalized greeting message, including the user's name, age, and favorite color, using proper formatting and grammar. Ensure the program handles invalid inputs, such as non-integer age values.",
    "difficulty": "superhard",
    "topics": [
        "input/output",
        "error handling",
        "string formatting"
    ],
    "sample_input": "John\n25\nBlue",
    "sample_output": "Hello, John! You are 25 years old and your favorite color is Blue."
}